README.md
setup.py
luigi_credstash/__init__.py
luigi_credstash/credential_mixin.py
luigi_credstash.egg-info/PKG-INFO
luigi_credstash.egg-info/SOURCES.txt
luigi_credstash.egg-info/dependency_links.txt
luigi_credstash.egg-info/not-zip-safe
luigi_credstash.egg-info/requires.txt
luigi_credstash.egg-info/top_level.txt