Metadata-Version: 1.1
Name: luigi-credstash
Version: 0.0.1
Summary: Easily use credstash with a Luigi configuration file.
Home-page: https://github.com/centriam/luigi-credstash
Author: Mike Bjerkness
Author-email: mike.bjerkness@centriam.com
License: MIT
Keywords: credstash,luigi
Platform: UNKNOWN
Classifier: Development Status :: 3 - Alpha
Classifier: Environment :: Console
Classifier: Environment :: Web Environment
Classifier: Intended Audience :: Developers
Classifier: Intended Audience :: System Administrators
Classifier: License :: OSI Approved :: MIT License
Classifier: Operating System :: OS Independent
Classifier: Programming Language :: Python
Classifier: Programming Language :: Python :: 2
Classifier: Programming Language :: Python :: 2.7
Classifier: Programming Language :: Python :: 3
Classifier: Programming Language :: Python :: 3.4
Classifier: Programming Language :: Python :: 3.5
Classifier: Programming Language :: Python :: 3.6
Classifier: Topic :: Security
Classifier: Topic :: Utilities
